phrase_translator/__init__.py
phrase_translator/dictionary_sources.py
phrase_translator/phrase_translator.py
phrase_translator/types.py
phrase_translator-0.1.2.dist-info/LICENSE
phrase_translator-0.1.2.dist-info/WHEEL
phrase_translator-0.1.2.dist-info/METADATA
phrase_translator-0.1.2.dist-info/RECORD
