Metadata-Version: 2.1
Name: phrase-translator
Version: 0.1.2
Summary: A very simple package to translate single words and phrases between different languages.
License: MIT
Author: Fabian Richter
Author-email: me@fr2501.com
Requires-Python: >=3.7,<4.0
Classifier: License :: OSI Approved :: MIT License
Classifier: Programming Language :: Python :: 3
Classifier: Programming Language :: Python :: 3.10
Classifier: Programming Language :: Python :: 3.7
Classifier: Programming Language :: Python :: 3.8
Classifier: Programming Language :: Python :: 3.9
Requires-Dist: wn (>=0.9.1,<0.10.0)
